<?xml version="1.0" encoding="utf-8"?>
<resources>
    <!--
        Generic SP definitionere
        Do not define other custom SP h
        Name definition should be like : spxxxx = xxx.0sp
    -->
    <dimen name="sp1">1.0sp</dimen>
    <dimen name="sp2">2.0sp</dimen>
    <dimen name="sp3">3.0sp</dimen>
    <dimen name="sp4">4.0sp</dimen>
    <dimen name="sp5">5.0sp</dimen>
    <dimen name="sp6">6.0sp</dimen>
    <dimen name="sp7">7.0sp</dimen>
    <dimen name="sp8">8.0sp</dimen>
    <dimen name="sp9">9.0sp</dimen>
    <dimen name="sp10">10.0sp</dimen>
    <dimen name="sp11">11.0sp</dimen>
    <dimen name="sp12">12.0sp</dimen>
    <dimen name="sp13">13.0sp</dimen>
    <dimen name="sp14">14.0sp</dimen>
    <dimen name="sp15">15.0sp</dimen>
    <dimen name="sp16">16.0sp</dimen>
    <dimen name="sp17">17.0sp</dimen>
    <dimen name="sp18">18.0sp</dimen>
    <dimen name="sp19">19.0sp</dimen>
    <dimen name="sp20">20.0sp</dimen>
    <dimen name="sp21">21.0sp</dimen>
    <dimen name="sp22">22.0sp</dimen>
    <dimen name="sp23">23.0sp</dimen>
    <dimen name="sp24">24.0sp</dimen>
    <dimen name="sp25">25.0sp</dimen>
    <dimen name="sp26">26.0sp</dimen>
    <dimen name="sp27">27.0sp</dimen>
    <dimen name="sp28">28.0sp</dimen>
    <dimen name="sp29">29.0sp</dimen>
    <dimen name="sp30">30.0sp</dimen>
    <dimen name="sp31">31.0sp</dimen>
    <dimen name="sp32">32.0sp</dimen>
    <dimen name="sp33">33.0sp</dimen>
    <dimen name="sp34">34.0sp</dimen>
    <dimen name="sp35">35.0sp</dimen>
    <dimen name="sp36">36.0sp</dimen>
    <dimen name="sp37">37.0sp</dimen>
    <dimen name="sp38">38.0sp</dimen>
    <dimen name="sp39">39.0sp</dimen>
    <dimen name="sp40">40.0sp</dimen>
    <dimen name="sp41">41.0sp</dimen>
    <dimen name="sp42">42.0sp</dimen>
    <dimen name="sp43">43.0sp</dimen>
    <dimen name="sp44">44.0sp</dimen>
    <dimen name="sp45">45.0sp</dimen>
    <dimen name="sp46">46.0sp</dimen>
    <dimen name="sp47">47.0sp</dimen>
    <dimen name="sp48">48.0sp</dimen>
    <dimen name="sp49">49.0sp</dimen>
    <dimen name="sp50">50.0sp</dimen>
    <dimen name="sp51">51.0sp</dimen>
    <dimen name="sp52">52.0sp</dimen>
    <dimen name="sp53">53.0sp</dimen>
    <dimen name="sp54">54.0sp</dimen>
    <dimen name="sp55">55.0sp</dimen>
    <dimen name="sp56">56.0sp</dimen>
    <dimen name="sp57">57.0sp</dimen>
    <dimen name="sp58">58.0sp</dimen>
    <dimen name="sp59">59.0sp</dimen>
    <dimen name="sp60">60.0sp</dimen>
    <dimen name="sp61">61.0sp</dimen>
    <dimen name="sp62">62.0sp</dimen>
    <dimen name="sp63">63.0sp</dimen>
    <dimen name="sp64">64.0sp</dimen>
    <dimen name="sp65">65.0sp</dimen>
    <dimen name="sp66">66.0sp</dimen>
    <dimen name="sp67">67.0sp</dimen>
    <dimen name="sp68">68.0sp</dimen>
    <dimen name="sp69">69.0sp</dimen>
    <dimen name="sp70">70.0sp</dimen>

    <!--
        Generic DP definition
        Do not define other custom DP here
        Name definition should be like : dpxxxx = xxx.0dp
    -->
    <dimen name="dp0">0.00dp</dimen>
    <dimen name="dp1">0.50dp</dimen>
    <dimen name="dp2">1.00dp</dimen>
    <dimen name="dp3">1.50dp</dimen>
    <dimen name="dp4">2.00dp</dimen>
    <dimen name="dp5">2.50dp</dimen>
    <dimen name="dp6">3.00dp</dimen>
    <dimen name="dp7">3.50dp</dimen>
    <dimen name="dp8">4.00dp</dimen>
    <dimen name="dp9">4.50dp</dimen>
    <dimen name="dp10">5.00dp</dimen>
    <dimen name="dp11">5.50dp</dimen>
    <dimen name="dp12">6.00dp</dimen>
    <dimen name="dp13">6.50dp</dimen>
    <dimen name="dp14">7.00dp</dimen>
    <dimen name="dp15">7.50dp</dimen>
    <dimen name="dp16">8.00dp</dimen>
    <dimen name="dp17">8.50dp</dimen>
    <dimen name="dp18">9.00dp</dimen>
    <dimen name="dp19">9.50dp</dimen>
    <dimen name="dp20">10.00dp</dimen>
    <dimen name="dp21">10.50dp</dimen>
    <dimen name="dp22">11.00dp</dimen>
    <dimen name="dp23">11.50dp</dimen>
    <dimen name="dp24">12.00dp</dimen>
    <dimen name="dp25">12.50dp</dimen>
    <dimen name="dp26">13.00dp</dimen>
    <dimen name="dp27">13.50dp</dimen>
    <dimen name="dp28">14.00dp</dimen>
    <dimen name="dp29">14.50dp</dimen>
    <dimen name="dp30">15.00dp</dimen>
    <dimen name="dp31">15.50dp</dimen>
    <dimen name="dp32">16.00dp</dimen>
    <dimen name="dp33">16.50dp</dimen>
    <dimen name="dp34">17.00dp</dimen>
    <dimen name="dp35">17.50dp</dimen>
    <dimen name="dp36">18.00dp</dimen>
    <dimen name="dp37">18.50dp</dimen>
    <dimen name="dp38">19.00dp</dimen>
    <dimen name="dp39">19.50dp</dimen>
    <dimen name="dp40">20.00dp</dimen>
    <dimen name="dp41">20.50dp</dimen>
    <dimen name="dp42">21.00dp</dimen>
    <dimen name="dp43">21.50dp</dimen>
    <dimen name="dp44">22.00dp</dimen>
    <dimen name="dp45">22.50dp</dimen>
    <dimen name="dp46">23.00dp</dimen>
    <dimen name="dp47">23.50dp</dimen>
    <dimen name="dp48">24.00dp</dimen>
    <dimen name="dp49">24.50dp</dimen>
    <dimen name="dp50">25.00dp</dimen>
    <dimen name="dp51">25.50dp</dimen>
    <dimen name="dp52">26.00dp</dimen>
    <dimen name="dp53">26.50dp</dimen>
    <dimen name="dp54">27.00dp</dimen>
    <dimen name="dp55">27.50dp</dimen>
    <dimen name="dp56">28.00dp</dimen>
    <dimen name="dp57">28.50dp</dimen>
    <dimen name="dp58">29.00dp</dimen>
    <dimen name="dp59">29.50dp</dimen>
    <dimen name="dp60">30.00dp</dimen>
    <dimen name="dp61">30.50dp</dimen>
    <dimen name="dp62">31.00dp</dimen>
    <dimen name="dp63">31.50dp</dimen>
    <dimen name="dp64">32.00dp</dimen>
    <dimen name="dp65">32.50dp</dimen>
    <dimen name="dp66">33.00dp</dimen>
    <dimen name="dp67">33.50dp</dimen>
    <dimen name="dp68">34.00dp</dimen>
    <dimen name="dp69">34.50dp</dimen>
    <dimen name="dp70">35.00dp</dimen>
    <dimen name="dp71">35.50dp</dimen>
    <dimen name="dp72">36.00dp</dimen>
    <dimen name="dp73">36.50dp</dimen>
    <dimen name="dp74">37.00dp</dimen>
    <dimen name="dp75">37.50dp</dimen>
    <dimen name="dp76">38.00dp</dimen>
    <dimen name="dp77">38.50dp</dimen>
    <dimen name="dp78">39.00dp</dimen>
    <dimen name="dp79">39.50dp</dimen>
    <dimen name="dp80">40.00dp</dimen>
    <dimen name="dp81">40.50dp</dimen>
    <dimen name="dp82">41.00dp</dimen>
    <dimen name="dp83">41.50dp</dimen>
    <dimen name="dp84">42.00dp</dimen>
    <dimen name="dp85">42.50dp</dimen>
    <dimen name="dp86">43.00dp</dimen>
    <dimen name="dp87">43.50dp</dimen>
    <dimen name="dp88">44.00dp</dimen>
    <dimen name="dp89">44.50dp</dimen>
    <dimen name="dp90">45.00dp</dimen>
    <dimen name="dp91">45.50dp</dimen>
    <dimen name="dp92">46.00dp</dimen>
    <dimen name="dp93">46.50dp</dimen>
    <dimen name="dp94">47.00dp</dimen>
    <dimen name="dp95">47.50dp</dimen>
    <dimen name="dp96">48.00dp</dimen>
    <dimen name="dp97">48.50dp</dimen>
    <dimen name="dp98">49.00dp</dimen>
    <dimen name="dp99">49.50dp</dimen>
    <dimen name="dp100">50.00dp</dimen>
    <dimen name="dp101">50.50dp</dimen>
    <dimen name="dp102">51.00dp</dimen>
    <dimen name="dp103">51.50dp</dimen>
    <dimen name="dp104">52.00dp</dimen>
    <dimen name="dp105">52.50dp</dimen>
    <dimen name="dp106">53.00dp</dimen>
    <dimen name="dp107">53.50dp</dimen>
    <dimen name="dp108">54.00dp</dimen>
    <dimen name="dp109">54.50dp</dimen>
    <dimen name="dp110">55.00dp</dimen>
    <dimen name="dp111">55.50dp</dimen>
    <dimen name="dp112">56.00dp</dimen>
    <dimen name="dp113">56.50dp</dimen>
    <dimen name="dp114">57.00dp</dimen>
    <dimen name="dp115">57.50dp</dimen>
    <dimen name="dp116">57.50dp</dimen>
    <dimen name="dp117">58.50dp</dimen>
    <dimen name="dp118">59.00dp</dimen>
    <dimen name="dp119">59.50dp</dimen>
    <dimen name="dp120">60.00dp</dimen>
    <dimen name="dp121">60.50dp</dimen>
    <dimen name="dp122">61.00dp</dimen>
    <dimen name="dp123">61.50dp</dimen>
    <dimen name="dp124">62.00dp</dimen>
    <dimen name="dp125">62.50dp</dimen>
    <dimen name="dp126">62.50dp</dimen>
    <dimen name="dp127">63.50dp</dimen>
    <dimen name="dp128">64.00dp</dimen>
    <dimen name="dp129">64.50dp</dimen>
    <dimen name="dp130">65.00dp</dimen>
    <dimen name="dp131">65.50dp</dimen>
    <dimen name="dp132">66.00dp</dimen>
    <dimen name="dp133">66.50dp</dimen>
    <dimen name="dp134">67.00dp</dimen>
    <dimen name="dp135">67.50dp</dimen>
    <dimen name="dp136">67.50dp</dimen>
    <dimen name="dp137">68.50dp</dimen>
    <dimen name="dp138">69.00dp</dimen>
    <dimen name="dp139">69.50dp</dimen>
    <dimen name="dp140">70.00dp</dimen>
    <dimen name="dp141">70.50dp</dimen>
    <dimen name="dp142">71.00dp</dimen>
    <dimen name="dp143">71.50dp</dimen>
    <dimen name="dp144">72.00dp</dimen>
    <dimen name="dp145">72.50dp</dimen>
    <dimen name="dp146">72.50dp</dimen>
    <dimen name="dp147">73.50dp</dimen>
    <dimen name="dp148">74.00dp</dimen>
    <dimen name="dp149">74.50dp</dimen>
    <dimen name="dp150">75.00dp</dimen>
    <dimen name="dp151">75.50dp</dimen>
    <dimen name="dp152">76.00dp</dimen>
    <dimen name="dp153">76.50dp</dimen>
    <dimen name="dp154">77.00dp</dimen>
    <dimen name="dp155">77.50dp</dimen>
    <dimen name="dp156">77.50dp</dimen>
    <dimen name="dp157">78.50dp</dimen>
    <dimen name="dp158">79.00dp</dimen>
    <dimen name="dp159">79.50dp</dimen>
    <dimen name="dp160">80.00dp</dimen>
    <dimen name="dp161">80.50dp</dimen>
    <dimen name="dp162">81.00dp</dimen>
    <dimen name="dp163">81.50dp</dimen>
    <dimen name="dp164">82.00dp</dimen>
    <dimen name="dp165">82.50dp</dimen>
    <dimen name="dp166">82.50dp</dimen>
    <dimen name="dp167">83.50dp</dimen>
    <dimen name="dp168">84.00dp</dimen>
    <dimen name="dp169">84.50dp</dimen>
    <dimen name="dp170">85.00dp</dimen>
    <dimen name="dp171">85.50dp</dimen>
    <dimen name="dp172">86.00dp</dimen>
    <dimen name="dp173">86.50dp</dimen>
    <dimen name="dp174">87.00dp</dimen>
    <dimen name="dp175">87.50dp</dimen>
    <dimen name="dp176">87.50dp</dimen>
    <dimen name="dp177">88.50dp</dimen>
    <dimen name="dp178">89.00dp</dimen>
    <dimen name="dp179">89.50dp</dimen>
    <dimen name="dp180">90.00dp</dimen>
    <dimen name="dp181">90.50dp</dimen>
    <dimen name="dp182">91.00dp</dimen>
    <dimen name="dp183">91.50dp</dimen>
    <dimen name="dp184">92.00dp</dimen>
    <dimen name="dp185">92.50dp</dimen>
    <dimen name="dp186">92.50dp</dimen>
    <dimen name="dp187">93.50dp</dimen>
    <dimen name="dp188">94.00dp</dimen>
    <dimen name="dp189">94.50dp</dimen>
    <dimen name="dp190">95.00dp</dimen>
    <dimen name="dp191">95.50dp</dimen>
    <dimen name="dp192">96.00dp</dimen>
    <dimen name="dp193">96.50dp</dimen>
    <dimen name="dp194">97.00dp</dimen>
    <dimen name="dp195">97.50dp</dimen>
    <dimen name="dp196">97.50dp</dimen>
    <dimen name="dp197">98.50dp</dimen>
    <dimen name="dp198">99.00dp</dimen>
    <dimen name="dp199">99.50dp</dimen>
    <dimen name="dp200">100.00dp</dimen>
    <dimen name="dp201">100.50dp</dimen>
    <dimen name="dp202">101.00dp</dimen>
    <dimen name="dp203">101.50dp</dimen>
    <dimen name="dp204">102.00dp</dimen>
    <dimen name="dp205">102.50dp</dimen>
    <dimen name="dp206">102.50dp</dimen>
    <dimen name="dp207">103.50dp</dimen>
    <dimen name="dp208">104.00dp</dimen>
    <dimen name="dp209">104.50dp</dimen>
    <dimen name="dp210">105.00dp</dimen>
    <dimen name="dp216">108.00dp</dimen>
    <dimen name="dp219">109.50dp</dimen>
    <dimen name="dp220">110.00dp</dimen>
    <dimen name="dp225">112.50dp</dimen>
    <dimen name="dp230">115.00dp</dimen>
    <dimen name="dp235">117.50dp</dimen>
    <dimen name="dp238">119.00dp</dimen>
    <dimen name="dp240">120.00dp</dimen>
    <dimen name="dp245">122.50dp</dimen>
    <dimen name="dp250">125.00dp</dimen>
    <dimen name="dp267">133.50dp</dimen>
    <dimen name="dp270">135.00dp</dimen>
    <dimen name="dp275">137.50dp</dimen>
    <dimen name="dp277">138.50dp</dimen>
    <dimen name="dp280">140.00dp</dimen>
    <dimen name="dp285">142.50dp</dimen>
    <dimen name="dp289">144.50dp</dimen>
    <dimen name="dp293">146.50dp</dimen>
    <dimen name="dp300">150.00dp</dimen>
    <dimen name="dp301">150.50dp</dimen>
    <dimen name="dp302">151.00dp</dimen>
    <dimen name="dp306">153.00dp</dimen>
    <dimen name="dp320">160.00dp</dimen>
    <dimen name="dp325">162.50dp</dimen>
    <dimen name="dp338">169.00dp</dimen>
    <dimen name="dp355">177.50dp</dimen>
    <dimen name="dp360">180.00dp</dimen>
    <dimen name="dp365">182.50dp</dimen>
    <dimen name="dp370">185.00dp</dimen>
    <dimen name="dp402">201.00dp</dimen>
    <dimen name="dp410">205.00dp</dimen>
    <dimen name="dp422">211.00dp</dimen>
    <dimen name="dp472">236.00dp</dimen>
    <dimen name="dp500">250.00dp</dimen>
    <dimen name="dp560">280.00dp</dimen>
    <dimen name="dp600">300.00dp</dimen>
    <dimen name="dp640">320.00dp</dimen>
    <dimen name="dp130.00">130.00dp</dimen>
    <dimen name="dp165.00">165.00dp</dimen>
    <dimen name="dp950">462.50dp</dimen>
    <dimen name="dp465.00">465.00dp</dimen>
    <dimen name="dp640.00">640.00dp</dimen>
    <dimen name="dp183.50">183.50dp</dimen>
</resources>